[
   {
      "id": 0,
      "nombre_y_apellido": "Prueba0",
      "email": "Prueba0@Prueba0",
      "fecha_de_nacimiento": "2003-06-01",
      "pasword": "Prueba0Prueba0",
      "comfirmPasword": "Prueba0Prueba0",
      "imagenUsuario": "default-user.png"
   },
   {
      "id": 1,
      "nombre_y_apellido": "Prueba01",
      "email": "Prueba01@Prueba01",
      "fecha_de_nacimiento": "2003-06-01",
      "pasword": "Prueba01Prueba01",
      "comfirmPasword": "Prueba01Prueba01",
      "imagenUsuario": "default-user.png"
   }
]